<annotation>
  <folder>images</folder>
  <filename>sprite88.jpg</filename>
  <segmented>0</segmented>
  <size>
    <width>480</width>
    <height>360</height>
    <depth>3</depth>
  </size>
  <object>
    <name>sprite</name>
    <pose>Unspecified</pose>
    <truncated>0</truncated>
    <difficult>0</difficult>
    <bndbox>
      <xmin>136</xmin>
      <ymin>74</ymin>
      <xmax>217</xmax>
      <ymax>128</ymax>
    </bndbox>
  </object>
  <object>
    <name>sprite</name>
    <pose>Unspecified</pose>
    <truncated>0</truncated>
    <difficult>0</difficult>
    <bndbox>
      <xmin>119</xmin>
      <ymin>154</ymin>
      <xmax>149</xmax>
      <ymax>170</ymax>
    </bndbox>
  </object>
  <object>
    <name>sprite</name>
    <pose>Unspecified</pose>
    <truncated>0</truncated>
    <difficult>0</difficult>
    <bndbox>
      <xmin>173</xmin>
      <ymin>154</ymin>
      <xmax>200</xmax>
      <ymax>170</ymax>
    </bndbox>
  </object>
  <object>
    <name>sprite</name>
    <pose>Unspecified</pose>
    <truncated>0</truncated>
    <difficult>0</difficult>
    <bndbox>
      <xmin>225</xmin>
      <ymin>153</ymin>
      <xmax>250</xmax>
      <ymax>168</ymax>
    </bndbox>
  </object>
  <object>
    <name>sprite</name>
    <pose>Unspecified</pose>
    <truncated>0</truncated>
    <difficult>0</difficult>
    <bndbox>
      <xmin>61</xmin>
      <ymin>83</ymin>
      <xmax>80</xmax>
      <ymax>124</ymax>
    </bndbox>
  </object>
</annotation>
