<annotation>
  <folder>images</folder>
  <filename>pepsi753.png</filename>
  <segmented>0</segmented>
  <size>
    <width>1366</width>
    <height>685</height>
    <depth>3</depth>
  </size>
  <object>
    <name>pepsi</name>
    <pose>Unspecified</pose>
    <truncated>0</truncated>
    <difficult>0</difficult>
    <bndbox>
      <xmin>145</xmin>
      <ymin>246</ymin>
      <xmax>309</xmax>
      <ymax>401</ymax>
    </bndbox>
  </object>
  <object>
    <name>pepsi</name>
    <pose>Unspecified</pose>
    <truncated>0</truncated>
    <difficult>0</difficult>
    <bndbox>
      <xmin>145</xmin>
      <ymin>246</ymin>
      <xmax>313</xmax>
      <ymax>401</ymax>
    </bndbox>
  </object>
  <object>
    <name>pepsi</name>
    <pose>Unspecified</pose>
    <truncated>0</truncated>
    <difficult>0</difficult>
    <bndbox>
      <xmin>145</xmin>
      <ymin>242</ymin>
      <xmax>313</xmax>
      <ymax>401</ymax>
    </bndbox>
  </object>
  <object>
    <name>pepsi</name>
    <pose>Unspecified</pose>
    <truncated>0</truncated>
    <difficult>0</difficult>
    <bndbox>
      <xmin>894</xmin>
      <ymin>119</ymin>
      <xmax>976</xmax>
      <ymax>201</ymax>
    </bndbox>
  </object>
  <object>
    <name>pepsi</name>
    <pose>Unspecified</pose>
    <truncated>0</truncated>
    <difficult>0</difficult>
    <bndbox>
      <xmin>894</xmin>
      <ymin>122</ymin>
      <xmax>976</xmax>
      <ymax>201</ymax>
    </bndbox>
  </object>
  <object>
    <name>pepsi</name>
    <pose>Unspecified</pose>
    <truncated>0</truncated>
    <difficult>0</difficult>
    <bndbox>
      <xmin>897</xmin>
      <ymin>122</ymin>
      <xmax>976</xmax>
      <ymax>201</ymax>
    </bndbox>
  </object>
</annotation>
