<annotation>
  <folder>images</folder>
  <filename>pepsi659.png</filename>
  <segmented>0</segmented>
  <size>
    <width>164</width>
    <height>300</height>
    <depth>3</depth>
  </size>
  <object>
    <name>pepsi</name>
    <pose>Unspecified</pose>
    <truncated>0</truncated>
    <difficult>0</difficult>
    <bndbox>
      <xmin>20</xmin>
      <ymin>46</ymin>
      <xmax>138</xmax>
      <ymax>177</ymax>
    </bndbox>
  </object>
  <object>
    <name>pepsi</name>
    <pose>Unspecified</pose>
    <truncated>0</truncated>
    <difficult>0</difficult>
    <bndbox>
      <xmin>22</xmin>
      <ymin>48</ymin>
      <xmax>138</xmax>
      <ymax>177</ymax>
    </bndbox>
  </object>
</annotation>
