<annotation>
  <folder>images</folder>
  <filename>pepsi894.jpg</filename>
  <segmented>0</segmented>
  <size>
    <width>621</width>
    <height>414</height>
    <depth>3</depth>
  </size>
  <object>
    <name>pepsi</name>
    <pose>Unspecified</pose>
    <truncated>0</truncated>
    <difficult>0</difficult>
    <bndbox>
      <xmin>332</xmin>
      <ymin>0</ymin>
      <xmax>442</xmax>
      <ymax>159</ymax>
    </bndbox>
  </object>
  <object>
    <name>pepsi</name>
    <pose>Unspecified</pose>
    <truncated>0</truncated>
    <difficult>0</difficult>
    <bndbox>
      <xmin>332</xmin>
      <ymin>2</ymin>
      <xmax>442</xmax>
      <ymax>159</ymax>
    </bndbox>
  </object>
  <object>
    <name>pepsi</name>
    <pose>Unspecified</pose>
    <truncated>0</truncated>
    <difficult>0</difficult>
    <bndbox>
      <xmin>558</xmin>
      <ymin>114</ymin>
      <xmax>617</xmax>
      <ymax>231</ymax>
    </bndbox>
  </object>
</annotation>
