<annotation>
  <folder>images</folder>
  <filename>pepsi368.jpg</filename>
  <segmented>0</segmented>
  <size>
    <width>2520</width>
    <height>1455</height>
    <depth>3</depth>
  </size>
  <object>
    <name>pepsi</name>
    <pose>Unspecified</pose>
    <truncated>0</truncated>
    <difficult>0</difficult>
    <bndbox>
      <xmin>550</xmin>
      <ymin>407</ymin>
      <xmax>745</xmax>
      <ymax>575</ymax>
    </bndbox>
  </object>
  <object>
    <name>pepsi</name>
    <pose>Unspecified</pose>
    <truncated>0</truncated>
    <difficult>0</difficult>
    <bndbox>
      <xmin>567</xmin>
      <ymin>424</ymin>
      <xmax>745</xmax>
      <ymax>575</ymax>
    </bndbox>
  </object>
</annotation>
