<annotation>
  <folder>images</folder>
  <filename>pepsi863.jpg</filename>
  <segmented>0</segmented>
  <size>
    <width>424</width>
    <height>438</height>
    <depth>3</depth>
  </size>
  <object>
    <name>pepsi</name>
    <pose>Unspecified</pose>
    <truncated>0</truncated>
    <difficult>0</difficult>
    <bndbox>
      <xmin>30</xmin>
      <ymin>205</ymin>
      <xmax>73</xmax>
      <ymax>246</ymax>
    </bndbox>
  </object>
  <object>
    <name>pepsi</name>
    <pose>Unspecified</pose>
    <truncated>0</truncated>
    <difficult>0</difficult>
    <bndbox>
      <xmin>32</xmin>
      <ymin>205</ymin>
      <xmax>73</xmax>
      <ymax>246</ymax>
    </bndbox>
  </object>
  <object>
    <name>pepsi</name>
    <pose>Unspecified</pose>
    <truncated>0</truncated>
    <difficult>0</difficult>
    <bndbox>
      <xmin>96</xmin>
      <ymin>205</ymin>
      <xmax>137</xmax>
      <ymax>242</ymax>
    </bndbox>
  </object>
  <object>
    <name>pepsi</name>
    <pose>Unspecified</pose>
    <truncated>0</truncated>
    <difficult>0</difficult>
    <bndbox>
      <xmin>154</xmin>
      <ymin>204</ymin>
      <xmax>195</xmax>
      <ymax>242</ymax>
    </bndbox>
  </object>
</annotation>
