<annotation>
  <folder>images</folder>
  <filename>snickers251.jpg</filename>
  <segmented>0</segmented>
  <size>
    <width>340</width>
    <height>227</height>
    <depth>3</depth>
  </size>
  <object>
    <name>snickers</name>
    <pose>Unspecified</pose>
    <truncated>0</truncated>
    <difficult>0</difficult>
    <bndbox>
      <xmin>109</xmin>
      <ymin>43</ymin>
      <xmax>192</xmax>
      <ymax>106</ymax>
    </bndbox>
  </object>
  <object>
    <name>snickers</name>
    <pose>Unspecified</pose>
    <truncated>0</truncated>
    <difficult>0</difficult>
    <bndbox>
      <xmin>15</xmin>
      <ymin>113</ymin>
      <xmax>56</xmax>
      <ymax>164</ymax>
    </bndbox>
  </object>
  <object>
    <name>snickers</name>
    <pose>Unspecified</pose>
    <truncated>0</truncated>
    <difficult>0</difficult>
    <bndbox>
      <xmin>308</xmin>
      <ymin>90</ymin>
      <xmax>335</xmax>
      <ymax>188</ymax>
    </bndbox>
  </object>
  <object>
    <name>snickers</name>
    <pose>Unspecified</pose>
    <truncated>0</truncated>
    <difficult>0</difficult>
    <bndbox>
      <xmin>145</xmin>
      <ymin>95</ymin>
      <xmax>177</xmax>
      <ymax>145</ymax>
    </bndbox>
  </object>
</annotation>
