<annotation>
  <folder>images</folder>
  <filename>snickers335.jpg</filename>
  <segmented>0</segmented>
  <size>
    <width>1500</width>
    <height>1011</height>
    <depth>3</depth>
  </size>
  <object>
    <name>snickers</name>
    <pose>Unspecified</pose>
    <truncated>0</truncated>
    <difficult>0</difficult>
    <bndbox>
      <xmin>181</xmin>
      <ymin>301</ymin>
      <xmax>999</xmax>
      <ymax>740</ymax>
    </bndbox>
  </object>
  <object>
    <name>snickers</name>
    <pose>Unspecified</pose>
    <truncated>0</truncated>
    <difficult>0</difficult>
    <bndbox>
      <xmin>241</xmin>
      <ymin>251</ymin>
      <xmax>999</xmax>
      <ymax>740</ymax>
    </bndbox>
  </object>
</annotation>
