<annotation>
  <folder>images</folder>
  <filename>snickers203.jpg</filename>
  <segmented>0</segmented>
  <size>
    <width>300</width>
    <height>300</height>
    <depth>3</depth>
  </size>
  <object>
    <name>snickers</name>
    <pose>Unspecified</pose>
    <truncated>0</truncated>
    <difficult>0</difficult>
    <bndbox>
      <xmin>120</xmin>
      <ymin>108</ymin>
      <xmax>266</xmax>
      <ymax>187</ymax>
    </bndbox>
  </object>
  <object>
    <name>snickers</name>
    <pose>Unspecified</pose>
    <truncated>0</truncated>
    <difficult>0</difficult>
    <bndbox>
      <xmin>126</xmin>
      <ymin>110</ymin>
      <xmax>266</xmax>
      <ymax>187</ymax>
    </bndbox>
  </object>
  <object>
    <name>snickers</name>
    <pose>Unspecified</pose>
    <truncated>0</truncated>
    <difficult>0</difficult>
    <bndbox>
      <xmin>133</xmin>
      <ymin>64</ymin>
      <xmax>260</xmax>
      <ymax>87</ymax>
    </bndbox>
  </object>
  <object>
    <name>snickers</name>
    <pose>Unspecified</pose>
    <truncated>0</truncated>
    <difficult>0</difficult>
    <bndbox>
      <xmin>0</xmin>
      <ymin>35</ymin>
      <xmax>98</xmax>
      <ymax>94</ymax>
    </bndbox>
  </object>
  <object>
    <name>snickers</name>
    <pose>Unspecified</pose>
    <truncated>0</truncated>
    <difficult>0</difficult>
    <bndbox>
      <xmin>0</xmin>
      <ymin>100</ymin>
      <xmax>72</xmax>
      <ymax>123</ymax>
    </bndbox>
  </object>
  <object>
    <name>snickers</name>
    <pose>Unspecified</pose>
    <truncated>0</truncated>
    <difficult>0</difficult>
    <bndbox>
      <xmin>0</xmin>
      <ymin>97</ymin>
      <xmax>72</xmax>
      <ymax>123</ymax>
    </bndbox>
  </object>
  <object>
    <name>snickers</name>
    <pose>Unspecified</pose>
    <truncated>0</truncated>
    <difficult>0</difficult>
    <bndbox>
      <xmin>50</xmin>
      <ymin>157</ymin>
      <xmax>87</xmax>
      <ymax>194</ymax>
    </bndbox>
  </object>
  <object>
    <name>snickers</name>
    <pose>Unspecified</pose>
    <truncated>0</truncated>
    <difficult>0</difficult>
    <bndbox>
      <xmin>0</xmin>
      <ymin>166</ymin>
      <xmax>37</xmax>
      <ymax>196</ymax>
    </bndbox>
  </object>
  <object>
    <name>snickers</name>
    <pose>Unspecified</pose>
    <truncated>0</truncated>
    <difficult>0</difficult>
    <bndbox>
      <xmin>0</xmin>
      <ymin>234</ymin>
      <xmax>47</xmax>
      <ymax>299</ymax>
    </bndbox>
  </object>
  <object>
    <name>snickers</name>
    <pose>Unspecified</pose>
    <truncated>0</truncated>
    <difficult>0</difficult>
    <bndbox>
      <xmin>144</xmin>
      <ymin>203</ymin>
      <xmax>217</xmax>
      <ymax>273</ymax>
    </bndbox>
  </object>
  <object>
    <name>snickers</name>
    <pose>Unspecified</pose>
    <truncated>0</truncated>
    <difficult>0</difficult>
    <bndbox>
      <xmin>128</xmin>
      <ymin>203</ymin>
      <xmax>217</xmax>
      <ymax>277</ymax>
    </bndbox>
  </object>
  <object>
    <name>snickers</name>
    <pose>Unspecified</pose>
    <truncated>0</truncated>
    <difficult>0</difficult>
    <bndbox>
      <xmin>199</xmin>
      <ymin>0</ymin>
      <xmax>291</xmax>
      <ymax>28</ymax>
    </bndbox>
  </object>
  <object>
    <name>snickers</name>
    <pose>Unspecified</pose>
    <truncated>0</truncated>
    <difficult>0</difficult>
    <bndbox>
      <xmin>108</xmin>
      <ymin>0</ymin>
      <xmax>125</xmax>
      <ymax>37</ymax>
    </bndbox>
  </object>
  <object>
    <name>snickers</name>
    <pose>Unspecified</pose>
    <truncated>0</truncated>
    <difficult>0</difficult>
    <bndbox>
      <xmin>108</xmin>
      <ymin>0</ymin>
      <xmax>132</xmax>
      <ymax>37</ymax>
    </bndbox>
  </object>
  <object>
    <name>snickers</name>
    <pose>Unspecified</pose>
    <truncated>0</truncated>
    <difficult>0</difficult>
    <bndbox>
      <xmin>221</xmin>
      <ymin>253</ymin>
      <xmax>298</xmax>
      <ymax>299</ymax>
    </bndbox>
  </object>
</annotation>
