<annotation>
  <folder>images</folder>
  <filename>snickers150.png</filename>
  <segmented>0</segmented>
  <size>
    <width>250</width>
    <height>179</height>
    <depth>3</depth>
  </size>
  <object>
    <name>snickers</name>
    <pose>Unspecified</pose>
    <truncated>0</truncated>
    <difficult>0</difficult>
    <bndbox>
      <xmin>45</xmin>
      <ymin>67</ymin>
      <xmax>190</xmax>
      <ymax>102</ymax>
    </bndbox>
  </object>
  <object>
    <name>snickers</name>
    <pose>Unspecified</pose>
    <truncated>0</truncated>
    <difficult>0</difficult>
    <bndbox>
      <xmin>45</xmin>
      <ymin>69</ymin>
      <xmax>193</xmax>
      <ymax>102</ymax>
    </bndbox>
  </object>
  <object>
    <name>snickers</name>
    <pose>Unspecified</pose>
    <truncated>0</truncated>
    <difficult>0</difficult>
    <bndbox>
      <xmin>49</xmin>
      <ymin>69</ymin>
      <xmax>193</xmax>
      <ymax>102</ymax>
    </bndbox>
  </object>
</annotation>
