<annotation>
  <folder>images</folder>
  <filename>snickers313.jpg</filename>
  <segmented>0</segmented>
  <size>
    <width>1300</width>
    <height>956</height>
    <depth>3</depth>
  </size>
  <object>
    <name>snickers</name>
    <pose>Unspecified</pose>
    <truncated>0</truncated>
    <difficult>0</difficult>
    <bndbox>
      <xmin>339</xmin>
      <ymin>208</ymin>
      <xmax>1005</xmax>
      <ymax>613</ymax>
    </bndbox>
  </object>
  <object>
    <name>snickers</name>
    <pose>Unspecified</pose>
    <truncated>0</truncated>
    <difficult>0</difficult>
    <bndbox>
      <xmin>344</xmin>
      <ymin>208</ymin>
      <xmax>1005</xmax>
      <ymax>613</ymax>
    </bndbox>
  </object>
  <object>
    <name>snickers</name>
    <pose>Unspecified</pose>
    <truncated>0</truncated>
    <difficult>0</difficult>
    <bndbox>
      <xmin>344</xmin>
      <ymin>221</ymin>
      <xmax>1005</xmax>
      <ymax>613</ymax>
    </bndbox>
  </object>
  <object>
    <name>snickers</name>
    <pose>Unspecified</pose>
    <truncated>0</truncated>
    <difficult>0</difficult>
    <bndbox>
      <xmin>284</xmin>
      <ymin>203</ymin>
      <xmax>836</xmax>
      <ymax>475</ymax>
    </bndbox>
  </object>
  <object>
    <name>snickers</name>
    <pose>Unspecified</pose>
    <truncated>0</truncated>
    <difficult>0</difficult>
    <bndbox>
      <xmin>284</xmin>
      <ymin>203</ymin>
      <xmax>857</xmax>
      <ymax>475</ymax>
    </bndbox>
  </object>
  <object>
    <name>snickers</name>
    <pose>Unspecified</pose>
    <truncated>0</truncated>
    <difficult>0</difficult>
    <bndbox>
      <xmin>284</xmin>
      <ymin>208</ymin>
      <xmax>857</xmax>
      <ymax>475</ymax>
    </bndbox>
  </object>
  <object>
    <name>snickers</name>
    <pose>Unspecified</pose>
    <truncated>0</truncated>
    <difficult>0</difficult>
    <bndbox>
      <xmin>405</xmin>
      <ymin>413</ymin>
      <xmax>612</xmax>
      <ymax>532</ymax>
    </bndbox>
  </object>
</annotation>
