<annotation>
  <folder>images</folder>
  <filename>mcdonalds477.jpg</filename>
  <segmented>0</segmented>
  <size>
    <width>638</width>
    <height>359</height>
    <depth>3</depth>
  </size>
  <object>
    <name>mcdonalds</name>
    <pose>Unspecified</pose>
    <truncated>0</truncated>
    <difficult>0</difficult>
    <bndbox>
      <xmin>16</xmin>
      <ymin>0</ymin>
      <xmax>113</xmax>
      <ymax>87</ymax>
    </bndbox>
  </object>
  <object>
    <name>mcdonalds</name>
    <pose>Unspecified</pose>
    <truncated>0</truncated>
    <difficult>0</difficult>
    <bndbox>
      <xmin>12</xmin>
      <ymin>0</ymin>
      <xmax>113</xmax>
      <ymax>88</ymax>
    </bndbox>
  </object>
</annotation>
